pypkpd/__init__.py
pypkpd/hello_world.py
pypkpd-0.0.2.dist-info/METADATA
pypkpd-0.0.2.dist-info/WHEEL
pypkpd-0.0.2.dist-info/top_level.txt
pypkpd-0.0.2.dist-info/RECORD
