Metadata-Version: 2.1
Name: pypkpd
Version: 0.0.2
Summary: A small example package for basic population pharmacokinetic and pharmacodynamic analysis.
Home-page: UNKNOWN
License: UNKNOWN
Platform: UNKNOWN
Requires-Python: >=3.6
